tripcode.py
tripcode3-0.1.2.dev2.dist-info/LICENSE
tripcode3-0.1.2.dev2.dist-info/METADATA
tripcode3-0.1.2.dev2.dist-info/WHEEL
tripcode3-0.1.2.dev2.dist-info/top_level.txt
tripcode3-0.1.2.dev2.dist-info/RECORD
